MANIFEST.in
README.md
setup.cfg
setup.py
scone/__init__.py
scone.egg-info/PKG-INFO
scone.egg-info/SOURCES.txt
scone.egg-info/dependency_links.txt
scone.egg-info/entry_points.txt
scone.egg-info/requires.txt
scone.egg-info/top_level.txt
scone/common/__init__.py
scone/common/chanpro.py
scone/common/loader.py
scone/common/misc.py
scone/common/modeutils.py
scone/common/pools.py
scone/default/__init__.py
scone/default/recipes/__init__.py
scone/default/recipes/apk.py
scone/default/recipes/apt.py
scone/default/recipes/docker.py
scone/default/recipes/filesystem.py
scone/default/recipes/fridge.py
scone/default/recipes/imperative.py
scone/default/recipes/linux.py
scone/default/recipes/mysql.py
scone/default/recipes/postgres.py
scone/default/recipes/python.py
scone/default/recipes/systemd.py
scone/default/steps/__init__.py
scone/default/steps/basic_steps.py
scone/default/steps/filesystem_steps.py
scone/default/steps/fridge_steps.py
scone/default/steps/linux_steps.py
scone/default/steps/systemd_steps.py
scone/default/utensils/__init__.py
scone/default/utensils/basic_utensils.py
scone/default/utensils/db_utensils.py
scone/default/utensils/docker_utensils.py
scone/default/utensils/dynamic_dependencies.py
scone/default/utensils/linux_utensils.py
scone/head/__init__.py
scone/head/dag.py
scone/head/dependency_tracking.py
scone/head/dot_emitter.py
scone/head/exceptions.py
scone/head/head.py
scone/head/kitchen.py
scone/head/menu_reader.py
scone/head/recipe.py
scone/head/secrets.py
scone/head/sshconn.py
scone/head/utils.py
scone/head/variables.py
scone/head/cli/__init__.py
scone/head/cli/freezer.py
scone/head/cli/michelin.py
scone/head/grammar/__init__.py
scone/head/grammar/scoml.tx
scone/sous/__init__.py
scone/sous/__main__.py
scone/sous/utensils.py