Metadata-Version: 2.1
Name: scone
Version: 0.2.0
Summary: Simple CONfiguration Engine
Home-page: https://librepush.net/project/scone
Author: Olivier 'reivilibre'
Author-email: rei@librepush.net
License: UNKNOWN
Platform: UNKNOWN
Classifier: Programming Language :: Python
Classifier: Programming Language :: Python :: 3
Classifier: Programming Language :: Python :: 3.7
Classifier: Programming Language :: Python :: Implementation :: CPython
Classifier: Programming Language :: Python :: Implementation :: PyPy
Requires-Python: >=3.7.0
Provides-Extra: head
Provides-Extra: sous
Provides-Extra: sous-core
Provides-Extra: sous-pg
Provides-Extra: sous-mysql
Provides-Extra: docker
